cap_cake/__init__.py
cap_cake/capcake.py
capcake-0.0.1.dist-info/LICENSE
capcake-0.0.1.dist-info/METADATA
capcake-0.0.1.dist-info/WHEEL
capcake-0.0.1.dist-info/top_level.txt
capcake-0.0.1.dist-info/RECORD
