Metadata-Version: 2.1
Name: capcake
Version: 0.0.1
Summary: Package to capture network traffic
Home-page: https://github.com/soreana/capcake
Author: Sina Kashipazha
Author-email: esterlinkof@gmail.com
License: UNKNOWN
Project-URL: Bug Tracker, https://github.com/soreana/capcake/issues
Platform: UNKNOWN
Classifier: Programming Language :: Python :: 3
Classifier: License :: OSI Approved :: Apache Software License
Classifier: Operating System :: OS Independent
Classifier: Topic :: System :: Monitoring
Requires-Python: >=3.6
License-File: LICENSE
